comto_core/__init__.py
comto_core/file.py
comto_core/mix.py
comto_core/path.py
comto_core/regexp.py
comto_core/time.py
comto_core-2.0.0.dist-info/LICENSE
comto_core-2.0.0.dist-info/METADATA
comto_core-2.0.0.dist-info/WHEEL
comto_core-2.0.0.dist-info/top_level.txt
comto_core-2.0.0.dist-info/RECORD
